sheet/__init__.py
sheet/warmup_lr.py
sheet/collaters/__init__.py
sheet/collaters/non_intrusive.py
sheet/datasets/__init__.py
sheet/datasets/non_intrusive.py
sheet/losses/__init__.py
sheet/losses/basic_losses.py
sheet/losses/contrastive_loss.py
sheet/losses/nll_losses.py
sheet/models/__init__.py
sheet/models/alignnet.py
sheet/models/ldnet.py
sheet/models/ramp.py
sheet/models/ramp_simple.py
sheet/models/sslmos.py
sheet/models/sslmos_cbm.py
sheet/models/sslmos_u.py
sheet/models/utmos.py
sheet/modules/__init__.py
sheet/modules/utils.py
sheet/modules/ldnet/__init__.py
sheet/modules/ldnet/mobilenetv2.py
sheet/modules/ldnet/mobilenetv3.py
sheet/modules/ldnet/modules.py
sheet/nonparametric/__init__.py
sheet/nonparametric/datastore.py
sheet/schedulers/__init__.py
sheet/schedulers/schedulers.py
sheet/trainers/__init__.py
sheet/trainers/base.py
sheet/trainers/non_intrusive.py
sheet/trainers/ramp.py
sheet/utils/__init__.py
sheet/utils/download.py
sheet/utils/model_io.py
sheet/utils/types.py
sheet/utils/utils.py
sheet_sqa-0.2.5.dist-info/licenses/LICENSE
sheet_sqa-0.2.5.dist-info/METADATA
sheet_sqa-0.2.5.dist-info/WHEEL
sheet_sqa-0.2.5.dist-info/top_level.txt
sheet_sqa-0.2.5.dist-info/RECORD
